cookie_component/__init__.py
cookie_component/frontend/build/app.css
cookie_component/frontend/build/asset-manifest.json
cookie_component/frontend/build/index.html
cookie_component/frontend/build/static/js/main.09573a7c.js
cookie_component/frontend/build/static/js/main.09573a7c.js.LICENSE.txt
cookie_component/frontend/build/static/js/main.09573a7c.js.map
cookie_component-0.1.4.dist-info/LICENSE
cookie_component-0.1.4.dist-info/METADATA
cookie_component-0.1.4.dist-info/WHEEL
cookie_component-0.1.4.dist-info/top_level.txt
cookie_component-0.1.4.dist-info/RECORD
