Metadata-Version: 2.1
Name: cookie-component
Version: 0.1.4
Summary: Streamlit component that allows you to do work with cookies
Home-page: 
Author: Cem Bakar
Author-email: cembakar@gmail.com
Requires-Python: >=3.9
License-File: LICENSE
Requires-Dist: streamlit
Provides-Extra: devel
Requires-Dist: wheel ; extra == 'devel'
Requires-Dist: pytest ==7.4.0 ; extra == 'devel'
Requires-Dist: playwright ==1.36.0 ; extra == 'devel'
Requires-Dist: requests ==2.31.0 ; extra == 'devel'
Requires-Dist: pytest-playwright-snapshot ==1.0 ; extra == 'devel'
Requires-Dist: pytest-rerunfailures ==12.0 ; extra == 'devel'
